cloud_tasks_deferred_v2/__init__.py
cloud_tasks_deferred_v2/deferred.py
cloud_tasks_deferred_v2/flask.py
cloud_tasks_deferred_v2/wsgi.py
cloud_tasks_deferred_v2-0.0.6.dist-info/LICENSE
cloud_tasks_deferred_v2-0.0.6.dist-info/METADATA
cloud_tasks_deferred_v2-0.0.6.dist-info/WHEEL
cloud_tasks_deferred_v2-0.0.6.dist-info/top_level.txt
cloud_tasks_deferred_v2-0.0.6.dist-info/RECORD
