Metadata-Version: 2.1
Name: cloud-tasks-deferred-v2
Version: 0.0.6
Summary: A deferred library for Google Cloud Tasks
Home-page: https://github.com/nagolos/python-cloud-tasks-deferred-v2
Classifier: Development Status :: 3 - Alpha
Classifier: Intended Audience :: Developers
Classifier: License :: OSI Approved :: Apache Software License
Classifier: Programming Language :: Python :: 3
Classifier: Programming Language :: Python :: 3.7
Classifier: Programming Language :: Python :: 3.8
Classifier: Programming Language :: Python :: 3.9
License-File: LICENSE
Requires-Dist: google-cloud-tasks (>=2.0.0)
Provides-Extra: test
Requires-Dist: pytest ; extra == 'test'
